goosetest/__init__.py
goosetest/main.py
goosetest-0.0.1.dist-info/LICENSE
goosetest-0.0.1.dist-info/METADATA
goosetest-0.0.1.dist-info/WHEEL
goosetest-0.0.1.dist-info/top_level.txt
goosetest-0.0.1.dist-info/RECORD
