Metadata-Version: 2.1
Name: goosetest
Version: 0.0.1
Summary: goosetest
Author-email: goose <goose@mail.com>
Project-URL: Homepage, https://github.com/goose/goosetest
Project-URL: Bug Tracker, https://github.com/goose/goosetest/issues
Classifier: Programming Language :: Python :: 3
Classifier: License :: OSI Approved :: MIT License
Classifier: Operating System :: OS Independent
Requires-Python: >=3.6
License-File: LICENSE
